KerasJiaochengXingkongliang/README.md
KerasJiaochengXingkongliang/__init__.py
KerasJiaochengXingkongliang/__main__.py
KerasJiaochengXingkongliang/file.epub
KerasJiaochengXingkongliang/index.html
KerasJiaochengXingkongliang/css/__init__.py
KerasJiaochengXingkongliang/css/annotations.css
KerasJiaochengXingkongliang/css/main.css
KerasJiaochengXingkongliang/css/normalize.css
KerasJiaochengXingkongliang/css/popup.css
KerasJiaochengXingkongliang/font/__init__.py
KerasJiaochengXingkongliang/font/fontello.eot
KerasJiaochengXingkongliang/font/fontello.svg
KerasJiaochengXingkongliang/font/fontello.ttf
KerasJiaochengXingkongliang/font/fontello.woff
KerasJiaochengXingkongliang/img/__init__.py
KerasJiaochengXingkongliang/img/annotator-glyph-sprite.png
KerasJiaochengXingkongliang/img/annotator-icon-sprite.png
KerasJiaochengXingkongliang/img/apple-touch-icon.png
KerasJiaochengXingkongliang/img/cancelfullscreen.png
KerasJiaochengXingkongliang/img/close.png
KerasJiaochengXingkongliang/img/fullscreen.png
KerasJiaochengXingkongliang/img/loader.gif
KerasJiaochengXingkongliang/img/menu-icon.png
KerasJiaochengXingkongliang/img/save.png
KerasJiaochengXingkongliang/img/saved.png
KerasJiaochengXingkongliang/img/settings-s.png
KerasJiaochengXingkongliang/img/settings.png
KerasJiaochengXingkongliang/img/star.png
KerasJiaochengXingkongliang/js/__init__.py
KerasJiaochengXingkongliang/js/epub.js
KerasJiaochengXingkongliang/js/epub.min.js
KerasJiaochengXingkongliang/js/epub.min.map
KerasJiaochengXingkongliang/js/hooks.min.js
KerasJiaochengXingkongliang/js/hooks.min.map
KerasJiaochengXingkongliang/js/reader.js
KerasJiaochengXingkongliang/js/reader.js.map
KerasJiaochengXingkongliang/js/reader.min.js
KerasJiaochengXingkongliang/js/reader.min.map
KerasJiaochengXingkongliang/js/hooks/__init__.py
KerasJiaochengXingkongliang/js/hooks/extensions/__init__.py
KerasJiaochengXingkongliang/js/hooks/extensions/highlight.js
KerasJiaochengXingkongliang/js/libs/__init__.py
keras_jiaocheng_xingkongliang-2024.3.5.0.dist-info/METADATA
keras_jiaocheng_xingkongliang-2024.3.5.0.dist-info/WHEEL
keras_jiaocheng_xingkongliang-2024.3.5.0.dist-info/entry_points.txt
keras_jiaocheng_xingkongliang-2024.3.5.0.dist-info/top_level.txt
keras_jiaocheng_xingkongliang-2024.3.5.0.dist-info/RECORD
